EL02/Esercizio 3/mux_4x1_gate.v
module mux_4x1_gate (x0,x1,x2,x3,s0,s1,y);
    input x0,x1,x2,x3,s0,s1;
    output y;

    wire s0n, s1n;
    wire y0, y1, y2, y3;

    not(s0n, s0);
    not(s1n, s1);

    and(y0, s0n, s1n, x0);
    and(y1, s0n, s1, x1);
    and(y2, s0, s1n, x2);
    and(y3, s0, s1, x3);

    or(y,y0,y1,y2,y3);
endmodule

EL02/Esercizio 3/mux_4x1_tb.v
`timescale 1ns/1ps

// Definizione testbench
module testbench_mux_4x1 ();

    // input e output
    reg x0, x1, x2, x3; // ingressi del mux
    reg s0, s1; // selettori
    wire y; // uscita del mux

    //Device Under Test (livello gate)
    mux_4x1_gate DUT (
        .x0(x0),
        .x1(x1),
        .x2(x2),
        .x3(x3),
        .s0(s0),
        .s1(s1),
        .y(y)
    );

    // // Device Under Test (livello dataflow)
    // mux_4x1_dataflow DUT (
    //     .x0(x0),
    //     .x1(x1),
    //     .x2(x2),
    //     .x3(x3),
    //     .s0(s0),
    //     .s1(s1),
    //     .y(y)
    // );
    // // Device Under Test (livello comportamentale)
    // mux_4x1_behavioral DUT (
    //     .in_i(in_i),
    //     .sel_i(sel_i),
    //     .out_o(out_o)
    // );

    // Stimoli di test
    initial begin
        $dumpfile("mux_4x1_tb.vcd");
        $dumpvars(0, testbench_mux_4x1);

        // Test 1.0: Selettore 00
        x0 = 0; x1 = 0; x2 = 0; x3 = 0;
        s0 = 0; s1 = 0;
        #20; // Attesa di 20 ns

        // Test 1.1: Selettore 00
        x0 = 1; x1 = 0; x2 = 0; x3 = 0;
        s0 = 0; s1 = 0;
        #20; // Attesa di 20 ns

        // Test 2.0: Selettore 01
        x0 = 0; x1 = 0; x2 = 0; x3 = 0;
        s0 = 0; s1 = 1;
        #20; // Attesa di 20 ns
        // Test 2.1: Selettore 01
        x0 = 0; x1 = 1; x2 = 0; x3 = 0;
        s0 = 0; s1 = 1;
        #20; // Attesa di 20 ns

        // Test 3.0: Selettore 10
        x0 = 0; x1 = 0; x2 = 0; x3 = 0;
        s0 = 1; s1 = 0; 
        #20; // Attesa di 20 ns
        // Test 3.1: Selettore 10
        x0 = 0; x1 = 0; x2 = 1; x3 = 0;
        s0 = 1; s1 = 0;
        #20; // Attesa di 20 ns

        // Test 4.0: Selettore 11
        x0 = 0; x1 = 0; x2 = 0; x3 = 0;
        s0 = 1; s1 = 1;
        #20; // Attesa di 20 ns
        // Test 4.1: Selettore 11
        x0 = 0; x1 = 0; x2 = 0; x3 = 1;
        s0 = 1; s1 = 1;
        #20; // Attesa di 20 ns

        // Fine del test
        $finish;
    end

    initial begin
        $monitor("Time: %0t | x0=%b x1=%b x2=%b x3=%b | s0=%b s1=%b | y=%b", 
                 $time, x0, x1, x2, x3, s0, s1, y);
    end
endmodule

EL02/Esercizio 3/mux_4x1_tb.vcd
$date
	Wed May  7 14:46:21 2025
$end
$version
	Icarus Verilog
$end
$timescale
	1ps
$end
$scope module testbench_mux_4x1 $end
$var wire 1 ! y $end
$var reg 1 " s0 $end
$var reg 1 # s1 $end
$var reg 1 $ x0 $end
$var reg 1 % x1 $end
$var reg 1 & x2 $end
$var reg 1 ' x3 $end
$scope module DUT $end
$var wire 1 " s0 $end
$var wire 1 ( s0n $end
$var wire 1 # s1 $end
$var wire 1 ) s1n $end
$var wire 1 $ x0 $end
$var wire 1 % x1 $end
$var wire 1 & x2 $end
$var wire 1 ' x3 $end
$var wire 1 ! y $end
$var wire 1 * y0 $end
$var wire 1 + y1 $end
$var wire 1 , y2 $end
$var wire 1 - y3 $end
$upscope $end
$upscope $end
$enddefinitions $end
$comment Show the parameter values. $end
$dumpall
$end
#0
$dumpvars
0-
0,
0+
0*
1)
1(
0'
0&
0%
0$
0#
0"
0!
$end
#20000
1!
1*
1$
#40000
0!
0)
0*
1#
0$
#60000
1!
1+
1%
#80000
0!
1)
0(
0+
0#
1"
0%
#100000
1!
1,
1&
#120000
0!
0)
0,
1#
0&
#140000
1!
1-
1'
