mux21/mux2x1.v
module mux2x1 (a, b, c, select);
  input b, c, select;
  output reg a;

  always @(select or b or c) begin
    if (select) a=b;
    else        a=c;
  end
endmodule

mux21/mux2x1_tb.v
module mux2x1_tb;
  reg s, a1, a0;
  wire q;

  mux2x1 mux(.select(s), .b(a1), .c(a0), .a(q));

  initial begin
    $dumpfile("mux2x1_tb.vcd");
    $dumpvars(0, mux2x1_tb);
    //$monitor("[%0tns] s=%b, a1=%b, a0=%b, q=%b", $time, s, a1, a0, q);
    s = 1'b0; a1 = 1'b0; a0 = 1'b0;
    #10
    s = 1'b0; a1 = 1'b0; a0 = 1'b1;
    #10
    s = 1'b0; a1 = 1'b1; a0 = 1'b0;
    #10
    s = 1'b0; a1 = 1'b1; a0 = 1'b1;

    #10
    s = 1'b1; a1 = 1'b0; a0 = 1'b0;
    #10
    s = 1'b1; a1 = 1'b0; a0 = 1'b1;
    #10
    s = 1'b1; a1 = 1'b1; a0 = 1'b0;
    #10
    s = 1'b1; a1 = 1'b1; a0 = 1'b1;
  end

endmodule

mux21/compilati/mux2x1_tb.vcd
$date
	Tue Apr 29 11:16:46 2025
$end
$version
	Icarus Verilog
$end
$timescale
	1s
$end
$scope module mux2x1_tb $end
$var wire 1 ! q $end
$var reg 1 " a0 $end
$var reg 1 # a1 $end
$var reg 1 $ s $end
$scope module mux $end
$var wire 1 # b $end
$var wire 1 " c $end
$var wire 1 $ select $end
$var reg 1 ! a $end
$upscope $end
$upscope $end
$enddefinitions $end
$comment Show the parameter values. $end
$dumpall
$end
#0
$dumpvars
0$
0#
0"
0!
$end
#10
1!
1"
#20
0!
0"
1#
#30
1!
1"
#40
0!
0"
0#
1$
#50
1"
#60
1!
0"
1#
#70
1"
