EL03/ES2/mult4.v
module mod4_checker(in_1, in_2, rst, clk, out_o);
    input in_1, in_2; // Input del modulo
    input rst, clk; // Segnali di reset e clock
    output reg out_o; // Dichiarazione di output come reg

    localparam S0 = 1'b0;
    localparam S1 = 1'b1;

    reg state, next_state;
    
    initial begin
        $dumpfile("waveform.vcd");  // nome del file di output
        $dumpvars(0, dut);          // traccia tutti i segnali del modulo 'dut'
    end

    always @(posedge clk or posedge rst) begin
        if (rst) begin
            state <= S0; // Reset dello stato
        end else begin
            state <= next_state; // Aggiornamento dello stato
        end
    end

    always @(*) begin
        case (state)
            S0: begin
                case ({in_1,in_2}) 
                    2'b00: begin next_state=S0; out_o=1; end
                    2'b01, 2'b10: begin next_state=S1; out_o=0; end
                    2'b11: begin next_state=S0; out_o=0; end
                endcase
            end 
            S1: begin
                 case ({in_1,in_2})
                    2'b00: begin next_state=S0; out_o=0; end
                    2'b01, 2'b10: begin next_state=S1; out_o=0; end
                    2'b11: begin next_state=S0; out_o=1; end
                 endcase
            end
            default: begin
                next_state = S0;
                out_o = 0;
            end
        endcase
    end
endmodule

EL03/ES2/mult4_tb.v
module mult4_tb;
    // Segnali per il DUT (device under test)
    reg clk;
    reg rst;
    reg in_1, in_2;
    wire out_o;

    // Istanzia il modulo mod4_checker
    mod4_checker dut (
        .clk(clk),
        .rst(rst),
        .in_1(in_1),
        .in_2(in_2),
        .out_o(out_o)
    );

    // Generatore di clock: periodo 10 unità di tempo
    initial clk = 0;
    always #5 clk = ~clk;

    // Procedura di test
    initial begin
        // Inizializzazioni
        rst = 1; in_1 = 0; in_2 = 0;
        #12;    // attiva reset per 12 unità di tempo
        rst = 0;

        // Sequenza di test: esempio con bit per in_1 e in_2
        // Nota: ogni assegnazione dura un ciclo di clock (10 unità)

        // in_1 = 100100, in_2 = 100010
        apply_bits(1,1); // primo bit (MSB)
        apply_bits(0,0);
        apply_bits(0,0);
        apply_bits(1,0);
        apply_bits(0,1);
        apply_bits(0,0);

        // Fine simulazione dopo un po'
        #20;
        $finish;


    end

    // Task per applicare i bit e mostrare output
    task apply_bits;
        input b1;
        input b2;
    begin
        @(negedge clk);
        in_1 = b1;
        in_2 = b2;
        @(posedge clk);
        $display("Time %0t | in_1=%b in_2=%b | out_o=%b", $time, in_1, in_2, out_o);
    end
    endtask

endmodule

EL03/ES2/waveform.vcd
$date
	Fri May 16 13:06:46 2025
$end
$version
	Icarus Verilog
$end
$timescale
	1s
$end
$scope module mult4_tb $end
$scope module dut $end
$var wire 1 ! clk $end
$var wire 1 " in_1 $end
$var wire 1 # in_2 $end
$var wire 1 $ rst $end
$var parameter 1 % S0 $end
$var parameter 1 & S1 $end
$var reg 1 ' next_state $end
$var reg 1 ( out_o $end
$var reg 1 ) state $end
$upscope $end
$upscope $end
$enddefinitions $end
$comment Show the parameter values. $end
$dumpall
1&
0%
$end
#0
$dumpvars
0)
1(
0'
1$
0#
0"
0!
$end
#5
1!
#10
0!
#12
0$
#15
1!
#20
0(
1#
1"
0!
#25
1!
#30
1(
0#
0"
0!
#35
1!
#40
0!
#45
1!
#50
0(
1'
1"
0!
#55
1)
1!
#60
1#
0"
0!
#65
1!
#70
0'
0#
0!
#75
1(
0)
1!
